tap_salesforce_connect/__init__.py
tap_salesforce_connect/auth.py
tap_salesforce_connect/client.py
tap_salesforce_connect/streams.py
tap_salesforce_connect/tap.py
tap_salesforce_connect-0.1.5.dist-info/LICENSE
tap_salesforce_connect-0.1.5.dist-info/METADATA
tap_salesforce_connect-0.1.5.dist-info/entry_points.txt
tap_salesforce_connect-0.1.5.dist-info/WHEEL
tap_salesforce_connect-0.1.5.dist-info/RECORD
