Metadata-Version: 2.1
Name: tap-salesforce-connect
Version: 0.1.5
Summary: `tap-salesforce-connect` is a Singer tap for SalesforceConnect, built with the Meltano Singer SDK.
Home-page: https://github.com/Widen/tap-salesforce-connect
License: Apache 2.0
Keywords: ELT,SalesforceConnect
Author: Josh Lloyd
Requires-Python: >=3.7.1,<3.12
Classifier: License :: Other/Proprietary License
Classifier: Programming Language :: Python :: 3
Classifier: Programming Language :: Python :: 3.8
Classifier: Programming Language :: Python :: 3.9
Classifier: Programming Language :: Python :: 3.10
Classifier: Programming Language :: Python :: 3.11
Provides-Extra: s3
Requires-Dist: cached-property (>=1,<2)
Requires-Dist: fs-s3fs (>=1.1.1,<2.0.0) ; extra == "s3"
Requires-Dist: requests (>=2.28.2,<3.0.0)
Requires-Dist: singer-sdk (>=0.34.1,<0.35.0)
Project-URL: Repository, https://github.com/Widen/tap-salesforce-connect
